streamlit_crepe/__init__.py
streamlit_crepe/frontend/.parcelrc
streamlit_crepe/frontend/package-lock.json
streamlit_crepe/frontend/package.json
streamlit_crepe/frontend/tsconfig.json
streamlit_crepe/frontend/vite.config.ts
streamlit_crepe/frontend/build/bootstrap.min.css
streamlit_crepe/frontend/build/index.html
streamlit_crepe/frontend/build/streamlit-crepe.ttf
streamlit_crepe/frontend/build/streamlit-crepe.umd.js
streamlit_crepe/frontend/build/streamlit-crepe.woff
streamlit_crepe/frontend/build/streamlit-crepe.woff2
streamlit_crepe/frontend/build/streamlit-crepe10.ttf
streamlit_crepe/frontend/build/streamlit-crepe10.woff
streamlit_crepe/frontend/build/streamlit-crepe10.woff2
streamlit_crepe/frontend/build/streamlit-crepe11.ttf
streamlit_crepe/frontend/build/streamlit-crepe11.woff
streamlit_crepe/frontend/build/streamlit-crepe11.woff2
streamlit_crepe/frontend/build/streamlit-crepe12.ttf
streamlit_crepe/frontend/build/streamlit-crepe12.woff
streamlit_crepe/frontend/build/streamlit-crepe12.woff2
streamlit_crepe/frontend/build/streamlit-crepe13.ttf
streamlit_crepe/frontend/build/streamlit-crepe13.woff
streamlit_crepe/frontend/build/streamlit-crepe13.woff2
streamlit_crepe/frontend/build/streamlit-crepe14.ttf
streamlit_crepe/frontend/build/streamlit-crepe14.woff
streamlit_crepe/frontend/build/streamlit-crepe14.woff2
streamlit_crepe/frontend/build/streamlit-crepe15.ttf
streamlit_crepe/frontend/build/streamlit-crepe15.woff
streamlit_crepe/frontend/build/streamlit-crepe15.woff2
streamlit_crepe/frontend/build/streamlit-crepe16.ttf
streamlit_crepe/frontend/build/streamlit-crepe16.woff
streamlit_crepe/frontend/build/streamlit-crepe16.woff2
streamlit_crepe/frontend/build/streamlit-crepe17.ttf
streamlit_crepe/frontend/build/streamlit-crepe17.woff
streamlit_crepe/frontend/build/streamlit-crepe17.woff2
streamlit_crepe/frontend/build/streamlit-crepe18.ttf
streamlit_crepe/frontend/build/streamlit-crepe18.woff
streamlit_crepe/frontend/build/streamlit-crepe18.woff2
streamlit_crepe-0.1.5.dist-info/METADATA
streamlit_crepe-0.1.5.dist-info/WHEEL
streamlit_crepe-0.1.5.dist-info/top_level.txt
streamlit_crepe-0.1.5.dist-info/RECORD
