Metadata-Version: 2.4
Name: streamlit-crepe
Version: 0.1.5
Summary: Milkdown Crepe editor component for Streamlit
Home-page: https://github.com/yourusername/streamlit-crepe
Author: Alex Cherkasov
Author-email: your.email@example.com
License: MIT
Project-URL: Homepage, https://github.com/AlexanderCherkasov/streamlit-crepe
Project-URL: Repository, https://github.com/AlexanderCherkasov/streamlit-crepe.git
Project-URL: Issues, https://github.com/AlexanderCherkasov/streamlit-crepe/issues
Classifier: Programming Language :: Python :: 3
Classifier: License :: OSI Approved :: MIT License
Classifier: Operating System :: OS Independent
Requires-Python: >=3.7
Requires-Dist: streamlit>=1.42.0
Dynamic: author-email
Dynamic: home-page
Dynamic: requires-python
